seyfert-api/__init__.py
seyfert-api/client.py
seypert/__init__.py
seypert/client.py
tests/__init__.py
seyfert_rest_client-0.1.2.dist-info/LICENSE
seyfert_rest_client-0.1.2.dist-info/METADATA
seyfert_rest_client-0.1.2.dist-info/WHEEL
seyfert_rest_client-0.1.2.dist-info/top_level.txt
seyfert_rest_client-0.1.2.dist-info/RECORD
