Metadata-Version: 2.1
Name: seyfert-rest-client
Version: 0.1.2
Summary: REST client for seyfert wth python
Home-page: UNKNOWN
Author: bartkim0426
Author-email: bartkim0426@gmail.com
License: UNKNOWN
Platform: UNKNOWN
Classifier: Programming Language :: Python :: 3
Classifier: License :: OSI Approved :: MIT License
Classifier: Operating System :: OS Independent
